[
  {
    "title": "电视",
    "child": [
      {
        "img": "../images/0000116632.jpg",
        "title": "观影王面版55英寸",
        "price": "4799.00元"
      },
      {
        "img": "../images/0000116630.jpg",
        "title": "观影王2代纤薄55英寸",
        "price": "4599.00元"
      },
      {
        "img": "../images/0000116631.jpg",
        "title": "观影王高色斑55英寸",
        "price": "3799.00元"
      },
      {
        "img": "../images/0000116634.jpg",
        "title": "真4K561系列55英寸",
        "price": "3199.00元"
      },
      {
        "img": "../images/0000116632.jpg",
        "title": "观影王4K护眼版55英寸",
        "price": "2699.00元"
      }
    ]
  },
  {
    "title": "手机",
    "child": [
      {
        "img": "../images/0000172041.jpg",
        "title": "TCL-580箐英本色态度商务手机",
        "price": "1399.00元"
      },
      {
        "img": "../images/0000172043.jpg",
        "title": "TCl-950剑胆琴心内涵商务手机",
        "price": "3299.00元"
      },
      {
        "img": "../images/0000155454.jpg",
        "title": "TCL-750初现文艺气质手机",
        "price": "1599.00元"
      },
      {
        "img": "../images/0000155454.jpg",
        "title": "TCl-520初现 美颜气质手机",
        "price": "1299.00元"
      },
      {
        "img": "../images/0000102152.jpg",
        "title": "老人机升级版 纯净白",
        "price": "199.00元"
      }
    ]
  },
  {
    "title": "空调",
    "child": [
      {
        "img": "../images/0000178382.jpg",
        "title": "北斗天玑智能钛金 大2匹",
        "price": "4099.00元"
      },
      {
        "img": "../images/0000178382.jpg",
        "title": "天阔 纯铜冷暖 大1.5匹",
        "price": "1649.00元"
      },
      {
        "img": "../images/0000169523.jpg",
        "title": "单冷型移动空调 小 1匹",
        "price": "1899.00元"
      },
      {
        "img": "../images/0000169523.jpg",
        "title": "智能云钛金节能型1.5匹",
        "price": "1799.00元"
      }
    ]
  },
  {
    "title": "冰箱",
    "child": [
      {
        "img": "../images/0000116125.jpg",
        "title": "流光金属多门456L",
        "price": "2799.00元"
      },
      {
        "img": "../images/0000116064.jpg",
        "title": "精准控温对开门515L",
        "price": "2699.00元"
      },
      {
        "img": "../images/0000116125.jpg",
        "title": "德式经三门205L",
        "price": "1099.00元"
      },
      {
        "img": "../images/0000116064.jpg",
        "title": "德式经典双门171L",
        "price": "699.00元"
      },
      {
        "img": "../images/0000116061.jpg",
        "title": "家用小双门 芭蕾白118L",
        "price": "699.00元"
      }
    ]
  },
  {
    "title": "洗衣机",
    "child": [
      {
        "img": "../images/0000116064.jpg",
        "title": "家用节能变频滚筒8公斤",
        "price": "1899.00元"
      },
      {
        "img": "../images/0000116064.jpg",
        "title": "大屏滚筒7公斤",
        "price": "1299.00元"
      },
      {
        "img": "../images/0000169545.jpg",
        "title": "大容量的波轮8公斤",
        "price": "999.00元"
      },
      {
        "img": "../images/0000121368.jpg",
        "title": "德国轮播7公斤",
        "price": "899.00元"
      },
      {
        "img": "../images/0000116264.jpg",
        "title": "德国工艺波轮6公斤",
        "price": "749.00元"
      }
    ]
  },
  {
    "title": "健康电器",
    "child": [
      {
        "img": "../images/0000108915.jpg",
        "title": "金招式RO智能净水机",
        "price": "1899.00元"
      },
      {
        "img": "../images/0000108911.jpg",
        "title": "阿里云小智土豪净化器",
        "price": "999.00元"
      },
      {
        "img": "../images/0000101980.jpg",
        "title": "干湿两用 拖地一体机",
        "price": "1099.00元"
      },
      {
        "img": "../images/0000108914.jpg",
        "title": "第三代原汁魔法师",
        "price": "699.00元"
      },
      {
        "img": "../images/0000101982.jpg",
        "title": "床铺除以式 白色",
        "price": "299.00元"
      }
    ]
  },
  {
    "child": [
      {
        "img": "../images/xq_01.jpg",
        "title": "TCL-580菁英本色态度商务手机 素银",
        "title1": "5.0英寸AMOLED大屏 正面指纹 1300万摄像 全网通 3+32G",
        "price": "1899.00元",
        "title2": "立即购买"
      },
      {
        "img": "../images/xq_02.jpg",
        "title": "TCL-750 初现 文艺气质手机 月白",
        "title1": "【11.11】底价掀开！11月3日00:00开抢，仅售1099元,咨询客服",
        "price": "1599.00元",
        "title2": "立即购买"
      },
      {
        "img": "../images/xq_02.jpg",
        "title": "TCL-750 初现 文艺气质手机 雅金",
        "title1": "【11.11】底价掀开！11月3日00:00开抢，仅售1099元,咨询客服",
        "price": "1599.00元",
        "title2": "立即购买"
      },
      {
        "img": "../images/xq_03.jpg",
        "title": "TCL-750 初现 文艺气质手机 黛蓝",
        "title1": "【11.11】底价掀开！11月3日00:00开抢，仅售1099元,咨询客服",
        "price": "1599.00元",
        "title2": "立即购买"
      }
    ]
  },
  {
    "child": [
      {
        "img": "../images/xq_01.jpg",
        "title": "TCL-580菁英本色态度商务手机 素银",
        "title1": "5.0英寸AMOLED大屏 正面指纹 1300万摄像 全网通 3+32G",
        "price": "1399.00元",
        "title2": "立即购买"
      },
      {
        "img": "../images/xq_04.jpg",
        "title": "金属立体声耳机 魅力红",
        "title1": "TCL 精密铝合金音腔 CD纹专利技术 3.5mm镀金插头 畅想高动态立体声",
        "price": "99.00元",
        "title2": "立即购买"
      },
      {
        "img": "../images/xq_02.jpg",
        "title": "TCL-750 初现 文艺气质手机 雅金",
        "title1": "【11.11】底价掀开！11月3日00:00开抢，仅售1099元,咨询客服",
        "price": "1599.00元",
        "title2": "立即购买"
      },
      {
        "img": "../images/xq_03.jpg",
        "title": "TCL-750 初现 文艺气质手机 黛蓝",
        "title1": "【11.11】底价掀开！11月3日00:00开抢，仅售1099元,咨询客服",
        "price": "1599.00元",
        "title2": "立即购买"
      }
    ]
  }
]